cascade_ui/__init__.py
cascade_ui/app.py
cascade_ui/models.py
cascade_ui/server.py
cascade_ui/web/dist/index.html
cascade_ui/web/dist/logo.svg
cascade_ui/web/dist/assets/index-925b43c0.css
cascade_ui/web/dist/assets/index-cb28c666.js
cascade_ui/web/dist/assets/logo-99b39901.svg
cascade_ui-0.2.2.dist-info/licenses/LICENSE
cascade_ui-0.2.2.dist-info/METADATA
cascade_ui-0.2.2.dist-info/WHEEL
cascade_ui-0.2.2.dist-info/top_level.txt
cascade_ui-0.2.2.dist-info/RECORD
